isoquant_diff/__init__.py
isoquant_diff/isoquant_diff.py
isoquant_diff-0.1.0.dist-info/LICENSE.txt
isoquant_diff-0.1.0.dist-info/METADATA
isoquant_diff-0.1.0.dist-info/WHEEL
isoquant_diff-0.1.0.dist-info/entry_points.txt
isoquant_diff-0.1.0.dist-info/top_level.txt
isoquant_diff-0.1.0.dist-info/RECORD
