Metadata-Version: 2.1
Name: isoquant-diff
Version: 0.1.0
Summary: Find the difference between 2 Isoquant configs
Home-page: https://github.com/thiloschild/isoquant_diff
Author: Thilo Schild
Author-email: work@thilo-schild.de
License: MIT
Platform: UNKNOWN
Classifier: Programming Language :: Python :: 3
Classifier: License :: OSI Approved :: MIT License
Classifier: Operating System :: OS Independent
Requires-Python: >=3.6
Requires-Dist: configparser
Requires-Dist: pandas
Requires-Dist: xlrd
Requires-Dist: openpyxl
Requires-Dist: argparse
Requires-Dist: easygui
